[{"entreprise":"Jatri","secteur d'activité":"Finance","ville":"Nagorsk","région":16,"date de l'emprunt":"28/05/2022","durée":11,"date de fin":"3/27/2022","taux de base":4.1,"discount":0.56,"taux bonifié":4.06,"condition (GWh/an)":5.001,"condition (tCO2/an)":147.45,"dernière date d'observation":"7/28/2022","réalisation (GWh)":145.39,"réalisation (tCO2)":199.89},
{"entreprise":"Zoozzy","secteur d'activité":"Consumer Services","ville":"Presa","région":66,"date de l'emprunt":"04/04/2021","durée":11,"date de fin":"4/7/2022","taux de base":2.07,"discount":0.57,"taux bonifié":2.58,"condition (GWh/an)":4.296,"condition (tCO2/an)":120.92,"dernière date d'observation":"4/1/2022","réalisation (GWh)":35.6,"réalisation (tCO2)":118.98},
{"entreprise":"Rhynyx","secteur d'activité":"Finance","ville":"Bretaña","région":44,"date de l'emprunt":"12/04/2021","durée":18,"date de fin":"12/26/2022","taux de base":5.34,"discount":0.93,"taux bonifié":5.97,"condition (GWh/an)":0.146,"condition (tCO2/an)":104.35,"dernière date d'observation":"11/6/2022","réalisation (GWh)":76.77,"réalisation (tCO2)":152.42},
{"entreprise":"Teklist","secteur d'activité":"Health Care","ville":"Yangsa","région":53,"date de l'emprunt":"03/09/2020","durée":18,"date de fin":"10/16/2022","taux de base":5.74,"discount":0.53,"taux bonifié":3.04,"condition (GWh/an)":5.247,"condition (tCO2/an)":196.33,"dernière date d'observation":"6/4/2022","réalisation (GWh)":78.03,"réalisation (tCO2)":131.39},
{"entreprise":"Dablist","secteur d'activité":"Health Care","ville":"Altay sumu","région":63,"date de l'emprunt":"29/08/2020","durée":15,"date de fin":"10/22/2022","taux de base":2.75,"discount":0.5,"taux bonifié":5.26,"condition (GWh/an)":3.964,"condition (tCO2/an)":183.32,"dernière date d'observation":"1/17/2023","réalisation (GWh)":196.83,"réalisation (tCO2)":161.77},
{"entreprise":"Edgewire","secteur d'activité":"Energy","ville":"Cimaung Kidul","région":77,"date de l'emprunt":"04/07/2020","durée":13,"date de fin":"4/11/2022","taux de base":5.34,"discount":0.58,"taux bonifié":2.84,"condition (GWh/an)":4.088,"condition (tCO2/an)":189.29,"dernière date d'observation":"5/21/2022","réalisation (GWh)":199.87,"réalisation (tCO2)":171.39},
{"entreprise":"Skyble","secteur d'activité":"Health Care","ville":"Lemende","région":64,"date de l'emprunt":"20/08/2020","durée":10,"date de fin":"1/17/2023","taux de base":2.73,"discount":1.0,"taux bonifié":3.7,"condition (GWh/an)":2.729,"condition (tCO2/an)":123.51,"dernière date d'observation":"12/31/2022","réalisation (GWh)":191.51,"réalisation (tCO2)":197.28},
{"entreprise":"Flipstorm","secteur d'activité":"Finance","ville":"Los Nogales","région":1,"date de l'emprunt":"29/10/2022","durée":5,"date de fin":"7/16/2022","taux de base":3.68,"discount":0.7,"taux bonifié":4.59,"condition (GWh/an)":4.532,"condition (tCO2/an)":32.39,"dernière date d'observation":"4/12/2022","réalisation (GWh)":7.71,"réalisation (tCO2)":86.76},
{"entreprise":"Riffpath","secteur d'activité":"Finance","ville":"Khāsh","région":61,"date de l'emprunt":"12/05/2022","durée":8,"date de fin":"9/19/2022","taux de base":5.21,"discount":0.75,"taux bonifié":3.07,"condition (GWh/an)":1.639,"condition (tCO2/an)":60.16,"dernière date d'observation":"4/15/2022","réalisation (GWh)":49.44,"réalisation (tCO2)":149.29},
{"entreprise":"Plajo","secteur d'activité":"Health Care","ville":"Galátsi","région":32,"date de l'emprunt":"22/01/2020","durée":18,"date de fin":"5/15/2022","taux de base":3.22,"discount":0.03,"taux bonifié":2.69,"condition (GWh/an)":0.746,"condition (tCO2/an)":93.4,"dernière date d'observation":"4/3/2022","réalisation (GWh)":62.04,"réalisation (tCO2)":2.29},
{"entreprise":"Tekfly","secteur d'activité":"Energy","ville":"Ji’an","région":59,"date de l'emprunt":"06/08/2021","durée":4,"date de fin":"10/8/2022","taux de base":5.36,"discount":0.45,"taux bonifié":5.52,"condition (GWh/an)":1.933,"condition (tCO2/an)":45.11,"dernière date d'observation":"8/5/2022","réalisation (GWh)":101.76,"réalisation (tCO2)":54.28},
{"entreprise":"Zoomdog","secteur d'activité":"Consumer Services","ville":"Acli","région":89,"date de l'emprunt":"07/11/2021","durée":19,"date de fin":"5/5/2022","taux de base":5.26,"discount":0.07,"taux bonifié":5.23,"condition (GWh/an)":0.205,"condition (tCO2/an)":86.29,"dernière date d'observation":"7/20/2022","réalisation (GWh)":161.02,"réalisation (tCO2)":150.68},
{"entreprise":"Quaxo","secteur d'activité":"Basic Industries","ville":"Kodinsk","région":58,"date de l'emprunt":"12/06/2022","durée":19,"date de fin":"11/7/2022","taux de base":4.01,"discount":0.51,"taux bonifié":5.46,"condition (GWh/an)":3.927,"condition (tCO2/an)":107.06,"dernière date d'observation":"10/23/2022","réalisation (GWh)":67.51,"réalisation (tCO2)":118.78},
{"entreprise":"Leexo","secteur d'activité":"Finance","ville":"Ölgiy","région":51,"date de l'emprunt":"21/11/2022","durée":7,"date de fin":"5/31/2022","taux de base":4.36,"discount":0.64,"taux bonifié":5.85,"condition (GWh/an)":0.021,"condition (tCO2/an)":69.13,"dernière date d'observation":"12/20/2022","réalisation (GWh)":97.69,"réalisation (tCO2)":78.89},
{"entreprise":"Yombu","secteur d'activité":"Public Utilities","ville":"Qiucun","région":74,"date de l'emprunt":"28/12/2022","durée":16,"date de fin":"8/5/2022","taux de base":5.05,"discount":0.13,"taux bonifié":3.63,"condition (GWh/an)":2.742,"condition (tCO2/an)":101.08,"dernière date d'observation":"6/18/2022","réalisation (GWh)":150.74,"réalisation (tCO2)":17.15},
{"entreprise":"Shuffledrive","secteur d'activité":"Consumer Services","ville":"Datar","région":37,"date de l'emprunt":"20/12/2020","durée":13,"date de fin":"12/1/2022","taux de base":2.31,"discount":0.29,"taux bonifié":5.85,"condition (GWh/an)":1.225,"condition (tCO2/an)":157.93,"dernière date d'observation":"12/30/2022","réalisation (GWh)":199.44,"réalisation (tCO2)":39.81},
{"entreprise":"Kamba","secteur d'activité":"n/a","ville":"Velyki Kopany","région":81,"date de l'emprunt":"05/02/2023","durée":13,"date de fin":"8/21/2022","taux de base":3.01,"discount":0.07,"taux bonifié":3.7,"condition (GWh/an)":3.555,"condition (tCO2/an)":190.55,"dernière date d'observation":"9/25/2022","réalisation (GWh)":38.73,"réalisation (tCO2)":164.92},
{"entreprise":"Trunyx","secteur d'activité":"Consumer Services","ville":"Västervik","région":86,"date de l'emprunt":"12/01/2020","durée":6,"date de fin":"1/22/2023","taux de base":5.81,"discount":0.19,"taux bonifié":5.33,"condition (GWh/an)":1.446,"condition (tCO2/an)":116.16,"dernière date d'observation":"7/9/2022","réalisation (GWh)":158.12,"réalisation (tCO2)":136.58},
{"entreprise":"Dabtype","secteur d'activité":"Consumer Non-Durables","ville":"Poljčane","région":33,"date de l'emprunt":"11/01/2022","durée":20,"date de fin":"1/10/2023","taux de base":2.25,"discount":0.92,"taux bonifié":2.98,"condition (GWh/an)":1.571,"condition (tCO2/an)":143.14,"dernière date d'observation":"3/2/2022","réalisation (GWh)":175.59,"réalisation (tCO2)":77.71},
{"entreprise":"Kazio","secteur d'activité":"n/a","ville":"Stopnica","région":41,"date de l'emprunt":"07/05/2020","durée":14,"date de fin":"2/3/2023","taux de base":3.19,"discount":0.48,"taux bonifié":3.23,"condition (GWh/an)":2.282,"condition (tCO2/an)":113.34,"dernière date d'observation":"3/14/2022","réalisation (GWh)":58.91,"réalisation (tCO2)":49.79},
{"entreprise":"Pixonyx","secteur d'activité":"n/a","ville":"Sidem","région":43,"date de l'emprunt":"06/04/2020","durée":16,"date de fin":"3/11/2022","taux de base":5.3,"discount":0.54,"taux bonifié":5.32,"condition (GWh/an)":4.107,"condition (tCO2/an)":18.31,"dernière date d'observation":"4/8/2022","réalisation (GWh)":20.07,"réalisation (tCO2)":173.21},
{"entreprise":"Twimbo","secteur d'activité":"Basic Industries","ville":"Salamrejo","région":39,"date de l'emprunt":"26/02/2022","durée":18,"date de fin":"11/3/2022","taux de base":4.85,"discount":0.47,"taux bonifié":5.78,"condition (GWh/an)":1.107,"condition (tCO2/an)":59.73,"dernière date d'observation":"12/11/2022","réalisation (GWh)":13.24,"réalisation (tCO2)":27.97},
{"entreprise":"Innotype","secteur d'activité":"n/a","ville":"Anxiang","région":38,"date de l'emprunt":"30/04/2022","durée":8,"date de fin":"11/13/2022","taux de base":3.2,"discount":0.46,"taux bonifié":5.85,"condition (GWh/an)":0.261,"condition (tCO2/an)":45.7,"dernière date d'observation":"7/21/2022","réalisation (GWh)":90.4,"réalisation (tCO2)":198.46},
{"entreprise":"Divape","secteur d'activité":"Consumer Services","ville":"Mojo","région":39,"date de l'emprunt":"23/05/2022","durée":6,"date de fin":"6/2/2022","taux de base":4.12,"discount":0.34,"taux bonifié":4.97,"condition (GWh/an)":0.038,"condition (tCO2/an)":93.95,"dernière date d'observation":"4/22/2022","réalisation (GWh)":65.32,"réalisation (tCO2)":57.91},
{"entreprise":"Yodoo","secteur d'activité":"Capital Goods","ville":"Eskilstuna","région":56,"date de l'emprunt":"25/02/2022","durée":8,"date de fin":"2/13/2023","taux de base":4.9,"discount":0.1,"taux bonifié":3.71,"condition (GWh/an)":5.818,"condition (tCO2/an)":62.47,"dernière date d'observation":"11/29/2022","réalisation (GWh)":137.46,"réalisation (tCO2)":190.51},
{"entreprise":"Voomm","secteur d'activité":"n/a","ville":"Vereshchagino","région":65,"date de l'emprunt":"23/02/2021","durée":5,"date de fin":"12/24/2022","taux de base":4.86,"discount":0.04,"taux bonifié":2.68,"condition (GWh/an)":3.321,"condition (tCO2/an)":78.24,"dernière date d'observation":"4/26/2022","réalisation (GWh)":156.9,"réalisation (tCO2)":173.05},
{"entreprise":"Skyba","secteur d'activité":"n/a","ville":"Banos","région":91,"date de l'emprunt":"16/12/2022","durée":6,"date de fin":"4/12/2022","taux de base":4.41,"discount":0.56,"taux bonifié":5.8,"condition (GWh/an)":5.325,"condition (tCO2/an)":78.7,"dernière date d'observation":"4/24/2022","réalisation (GWh)":107.83,"réalisation (tCO2)":106.17},
{"entreprise":"Photobug","secteur d'activité":"Health Care","ville":"Bābol","région":2,"date de l'emprunt":"21/11/2021","durée":19,"date de fin":"8/22/2022","taux de base":3.55,"discount":0.03,"taux bonifié":4.04,"condition (GWh/an)":1.191,"condition (tCO2/an)":29.93,"dernière date d'observation":"4/15/2022","réalisation (GWh)":169.44,"réalisation (tCO2)":198.72},
{"entreprise":"Skinix","secteur d'activité":"Finance","ville":"Sendang","région":33,"date de l'emprunt":"28/04/2022","durée":9,"date de fin":"11/27/2022","taux de base":3.37,"discount":0.67,"taux bonifié":2.13,"condition (GWh/an)":1.335,"condition (tCO2/an)":27.55,"dernière date d'observation":"10/30/2022","réalisation (GWh)":139.73,"réalisation (tCO2)":175.83},
{"entreprise":"Skaboo","secteur d'activité":"Consumer Non-Durables","ville":"Mỹ Xuyên","région":3,"date de l'emprunt":"17/11/2021","durée":4,"date de fin":"12/11/2022","taux de base":5.94,"discount":0.07,"taux bonifié":5.84,"condition (GWh/an)":1.193,"condition (tCO2/an)":190.46,"dernière date d'observation":"5/20/2022","réalisation (GWh)":26.48,"réalisation (tCO2)":33.3},
{"entreprise":"Thoughtblab","secteur d'activité":"Health Care","ville":"Jiuzhen","région":39,"date de l'emprunt":"08/01/2021","durée":17,"date de fin":"11/7/2022","taux de base":4.6,"discount":0.59,"taux bonifié":3.91,"condition (GWh/an)":4.305,"condition (tCO2/an)":158.41,"dernière date d'observation":"10/30/2022","réalisation (GWh)":160.45,"réalisation (tCO2)":74.41},
{"entreprise":"Jazzy","secteur d'activité":"n/a","ville":"Nabire","région":2,"date de l'emprunt":"13/05/2022","durée":14,"date de fin":"12/16/2022","taux de base":3.64,"discount":0.51,"taux bonifié":4.38,"condition (GWh/an)":1.457,"condition (tCO2/an)":112.38,"dernière date d'observation":"1/12/2023","réalisation (GWh)":150.22,"réalisation (tCO2)":135.84},
{"entreprise":"Jaxnation","secteur d'activité":"n/a","ville":"Moutnice","région":78,"date de l'emprunt":"02/10/2022","durée":8,"date de fin":"12/3/2022","taux de base":3.46,"discount":0.15,"taux bonifié":4.04,"condition (GWh/an)":3.181,"condition (tCO2/an)":47.13,"dernière date d'observation":"6/12/2022","réalisation (GWh)":6.53,"réalisation (tCO2)":36.53},
{"entreprise":"Mymm","secteur d'activité":"Transportation","ville":"Huyu","région":42,"date de l'emprunt":"30/07/2021","durée":18,"date de fin":"8/1/2022","taux de base":4.66,"discount":0.75,"taux bonifié":2.14,"condition (GWh/an)":1.263,"condition (tCO2/an)":183.19,"dernière date d'observation":"10/30/2022","réalisation (GWh)":131.43,"réalisation (tCO2)":17.1},
{"entreprise":"Quinu","secteur d'activité":"Health Care","ville":"Lamu","région":66,"date de l'emprunt":"09/11/2022","durée":7,"date de fin":"9/3/2022","taux de base":3.72,"discount":0.74,"taux bonifié":4.69,"condition (GWh/an)":5.517,"condition (tCO2/an)":188.59,"dernière date d'observation":"11/4/2022","réalisation (GWh)":179.22,"réalisation (tCO2)":54.17},
{"entreprise":"Rhyloo","secteur d'activité":"Capital Goods","ville":"Seymchan","région":27,"date de l'emprunt":"21/01/2021","durée":17,"date de fin":"10/16/2022","taux de base":3.17,"discount":0.63,"taux bonifié":5.7,"condition (GWh/an)":1.221,"condition (tCO2/an)":86.61,"dernière date d'observation":"8/17/2022","réalisation (GWh)":42.98,"réalisation (tCO2)":198.49},
{"entreprise":"Pixoboo","secteur d'activité":"Finance","ville":"Sadov","région":11,"date de l'emprunt":"23/01/2021","durée":19,"date de fin":"7/20/2022","taux de base":3.93,"discount":0.5,"taux bonifié":3.22,"condition (GWh/an)":1.879,"condition (tCO2/an)":194.68,"dernière date d'observation":"9/26/2022","réalisation (GWh)":181.52,"réalisation (tCO2)":4.67},
{"entreprise":"Flashspan","secteur d'activité":"Health Care","ville":"Gaoqiaolou","région":7,"date de l'emprunt":"30/11/2022","durée":5,"date de fin":"6/29/2022","taux de base":2.03,"discount":0.76,"taux bonifié":5.3,"condition (GWh/an)":1.195,"condition (tCO2/an)":151.1,"dernière date d'observation":"7/27/2022","réalisation (GWh)":29.85,"réalisation (tCO2)":48.06},
{"entreprise":"Eire","secteur d'activité":"Capital Goods","ville":"Kafir Qala","région":22,"date de l'emprunt":"15/11/2020","durée":18,"date de fin":"1/4/2023","taux de base":3.13,"discount":0.83,"taux bonifié":5.99,"condition (GWh/an)":1.731,"condition (tCO2/an)":141.28,"dernière date d'observation":"7/11/2022","réalisation (GWh)":154.37,"réalisation (tCO2)":71.59},
{"entreprise":"Yozio","secteur d'activité":"n/a","ville":"Vanves","région":7,"date de l'emprunt":"20/07/2020","durée":6,"date de fin":"10/3/2022","taux de base":5.13,"discount":0.68,"taux bonifié":4.72,"condition (GWh/an)":5.376,"condition (tCO2/an)":16.26,"dernière date d'observation":"3/23/2022","réalisation (GWh)":186.92,"réalisation (tCO2)":197.63},
{"entreprise":"Youfeed","secteur d'activité":"Finance","ville":"Jixi","région":45,"date de l'emprunt":"03/02/2020","durée":14,"date de fin":"7/13/2022","taux de base":5.27,"discount":0.45,"taux bonifié":3.93,"condition (GWh/an)":0.539,"condition (tCO2/an)":49.59,"dernière date d'observation":"2/1/2023","réalisation (GWh)":56.27,"réalisation (tCO2)":107.44},
{"entreprise":"Flashset","secteur d'activité":"Consumer Services","ville":"Usol’ye","région":4,"date de l'emprunt":"31/01/2020","durée":11,"date de fin":"1/16/2023","taux de base":2.46,"discount":0.67,"taux bonifié":5.76,"condition (GWh/an)":3.413,"condition (tCO2/an)":169.68,"dernière date d'observation":"10/14/2022","réalisation (GWh)":80.75,"réalisation (tCO2)":72.81},
{"entreprise":"Edgeclub","secteur d'activité":"Health Care","ville":"Racine","région":60,"date de l'emprunt":"30/01/2020","durée":14,"date de fin":"6/13/2022","taux de base":4.87,"discount":0.23,"taux bonifié":5.06,"condition (GWh/an)":4.818,"condition (tCO2/an)":144.59,"dernière date d'observation":"9/28/2022","réalisation (GWh)":127.73,"réalisation (tCO2)":3.35},
{"entreprise":"Midel","secteur d'activité":"Public Utilities","ville":"Stříbro","région":3,"date de l'emprunt":"16/05/2021","durée":19,"date de fin":"12/28/2022","taux de base":3.92,"discount":0.43,"taux bonifié":5.07,"condition (GWh/an)":4.165,"condition (tCO2/an)":7.92,"dernière date d'observation":"12/27/2022","réalisation (GWh)":122.43,"réalisation (tCO2)":103.33},
{"entreprise":"Kanoodle","secteur d'activité":"n/a","ville":"Shangtianba","région":60,"date de l'emprunt":"29/07/2022","durée":20,"date de fin":"7/22/2022","taux de base":3.49,"discount":0.41,"taux bonifié":2.41,"condition (GWh/an)":4.766,"condition (tCO2/an)":107.94,"dernière date d'observation":"12/10/2022","réalisation (GWh)":58.06,"réalisation (tCO2)":142.54},
{"entreprise":"Tagpad","secteur d'activité":"Finance","ville":"Pļaviņas","région":88,"date de l'emprunt":"22/05/2020","durée":5,"date de fin":"9/4/2022","taux de base":3.15,"discount":0.69,"taux bonifié":2.11,"condition (GWh/an)":2.588,"condition (tCO2/an)":5.42,"dernière date d'observation":"10/18/2022","réalisation (GWh)":61.1,"réalisation (tCO2)":107.78},
{"entreprise":"Yodoo","secteur d'activité":"n/a","ville":"Karolinka","région":76,"date de l'emprunt":"09/06/2020","durée":6,"date de fin":"8/15/2022","taux de base":3.65,"discount":0.29,"taux bonifié":5.89,"condition (GWh/an)":5.294,"condition (tCO2/an)":185.83,"dernière date d'observation":"11/13/2022","réalisation (GWh)":137.32,"réalisation (tCO2)":42.25},
{"entreprise":"Skidoo","secteur d'activité":"Finance","ville":"Nagasari","région":39,"date de l'emprunt":"17/01/2020","durée":3,"date de fin":"12/29/2022","taux de base":4.43,"discount":0.39,"taux bonifié":2.02,"condition (GWh/an)":4.29,"condition (tCO2/an)":191.74,"dernière date d'observation":"5/11/2022","réalisation (GWh)":189.53,"réalisation (tCO2)":152.77},
{"entreprise":"Ooba","secteur d'activité":"n/a","ville":"Longkou","région":10,"date de l'emprunt":"13/05/2021","durée":3,"date de fin":"10/7/2022","taux de base":2.55,"discount":0.62,"taux bonifié":5.44,"condition (GWh/an)":3.833,"condition (tCO2/an)":136.05,"dernière date d'observation":"5/9/2022","réalisation (GWh)":153.53,"réalisation (tCO2)":151.1},
{"entreprise":"Skibox","secteur d'activité":"n/a","ville":"Shanggu","région":89,"date de l'emprunt":"24/11/2020","durée":8,"date de fin":"11/4/2022","taux de base":2.09,"discount":0.57,"taux bonifié":4.85,"condition (GWh/an)":0.464,"condition (tCO2/an)":2.3,"dernière date d'observation":"10/29/2022","réalisation (GWh)":185.9,"réalisation (tCO2)":10.39},
{"entreprise":"Dabjam","secteur d'activité":"n/a","ville":"Rios Frios","région":79,"date de l'emprunt":"10/09/2021","durée":16,"date de fin":"11/11/2022","taux de base":2.39,"discount":0.01,"taux bonifié":2.46,"condition (GWh/an)":0.252,"condition (tCO2/an)":177.55,"dernière date d'observation":"4/9/2022","réalisation (GWh)":115.94,"réalisation (tCO2)":148.76},
{"entreprise":"Devshare","secteur d'activité":"Technology","ville":"Longchiqiao","région":56,"date de l'emprunt":"01/11/2021","durée":15,"date de fin":"11/30/2022","taux de base":3.63,"discount":0.53,"taux bonifié":5.92,"condition (GWh/an)":0.694,"condition (tCO2/an)":37.91,"dernière date d'observation":"2/12/2023","réalisation (GWh)":78.05,"réalisation (tCO2)":29.99},
{"entreprise":"Dynazzy","secteur d'activité":"Consumer Durables","ville":"Maying","région":57,"date de l'emprunt":"21/01/2021","durée":10,"date de fin":"1/21/2023","taux de base":4.72,"discount":0.35,"taux bonifié":5.33,"condition (GWh/an)":0.472,"condition (tCO2/an)":88.25,"dernière date d'observation":"9/28/2022","réalisation (GWh)":53.77,"réalisation (tCO2)":177.4},
{"entreprise":"Skyndu","secteur d'activité":"Basic Industries","ville":"Wubao","région":88,"date de l'emprunt":"26/01/2022","durée":13,"date de fin":"2/6/2023","taux de base":2.46,"discount":0.35,"taux bonifié":3.01,"condition (GWh/an)":1.501,"condition (tCO2/an)":169.99,"dernière date d'observation":"11/18/2022","réalisation (GWh)":180.66,"réalisation (tCO2)":151.37},
{"entreprise":"Nlounge","secteur d'activité":"Health Care","ville":"Millerovo","région":7,"date de l'emprunt":"05/12/2022","durée":7,"date de fin":"12/29/2022","taux de base":5.8,"discount":0.56,"taux bonifié":4.01,"condition (GWh/an)":0.969,"condition (tCO2/an)":117.67,"dernière date d'observation":"9/30/2022","réalisation (GWh)":40.02,"réalisation (tCO2)":194.45},
{"entreprise":"Dablist","secteur d'activité":"Public Utilities","ville":"Rostov-na-Donu","région":78,"date de l'emprunt":"02/08/2021","durée":19,"date de fin":"1/4/2023","taux de base":5.59,"discount":0.28,"taux bonifié":5.54,"condition (GWh/an)":1.882,"condition (tCO2/an)":103.16,"dernière date d'observation":"5/3/2022","réalisation (GWh)":119.8,"réalisation (tCO2)":149.09},
{"entreprise":"Photobug","secteur d'activité":"Consumer Services","ville":"Mzuzu","région":88,"date de l'emprunt":"02/02/2022","durée":15,"date de fin":"3/28/2022","taux de base":3.96,"discount":0.45,"taux bonifié":3.62,"condition (GWh/an)":3.611,"condition (tCO2/an)":87.52,"dernière date d'observation":"8/22/2022","réalisation (GWh)":75.45,"réalisation (tCO2)":71.58},
{"entreprise":"Devify","secteur d'activité":"n/a","ville":"Sudikampir","région":42,"date de l'emprunt":"26/04/2021","durée":11,"date de fin":"11/11/2022","taux de base":5.98,"discount":0.76,"taux bonifié":4.75,"condition (GWh/an)":4.132,"condition (tCO2/an)":191.99,"dernière date d'observation":"5/27/2022","réalisation (GWh)":26.41,"réalisation (tCO2)":45.16},
{"entreprise":"Omba","secteur d'activité":"n/a","ville":"Tongole","région":52,"date de l'emprunt":"07/05/2022","durée":15,"date de fin":"11/10/2022","taux de base":5.53,"discount":0.04,"taux bonifié":3.26,"condition (GWh/an)":3.654,"condition (tCO2/an)":181.97,"dernière date d'observation":"11/8/2022","réalisation (GWh)":61.14,"réalisation (tCO2)":105.71},
{"entreprise":"Rhybox","secteur d'activité":"Consumer Non-Durables","ville":"Shumikha","région":54,"date de l'emprunt":"29/04/2022","durée":4,"date de fin":"4/14/2022","taux de base":3.87,"discount":0.53,"taux bonifié":5.18,"condition (GWh/an)":5.216,"condition (tCO2/an)":192.36,"dernière date d'observation":"2/8/2023","réalisation (GWh)":177.05,"réalisation (tCO2)":18.55},
{"entreprise":"Rhybox","secteur d'activité":"n/a","ville":"Nakhon Pathom","région":40,"date de l'emprunt":"14/09/2022","durée":11,"date de fin":"9/24/2022","taux de base":5.88,"discount":0.43,"taux bonifié":2.24,"condition (GWh/an)":3.041,"condition (tCO2/an)":76.65,"dernière date d'observation":"11/9/2022","réalisation (GWh)":198.65,"réalisation (tCO2)":75.08},
{"entreprise":"Feedspan","secteur d'activité":"Capital Goods","ville":"Kavallári","région":67,"date de l'emprunt":"16/11/2022","durée":4,"date de fin":"7/12/2022","taux de base":4.25,"discount":0.52,"taux bonifié":2.61,"condition (GWh/an)":2.067,"condition (tCO2/an)":171.21,"dernière date d'observation":"8/19/2022","réalisation (GWh)":13.42,"réalisation (tCO2)":132.08},
{"entreprise":"Agimba","secteur d'activité":"n/a","ville":"Itajaí","région":3,"date de l'emprunt":"23/04/2020","durée":2,"date de fin":"4/23/2022","taux de base":3.67,"discount":0.52,"taux bonifié":5.61,"condition (GWh/an)":5.17,"condition (tCO2/an)":78.45,"dernière date d'observation":"3/8/2022","réalisation (GWh)":195.33,"réalisation (tCO2)":15.23},
{"entreprise":"Twinder","secteur d'activité":"Consumer Durables","ville":"Azacualpa","région":44,"date de l'emprunt":"26/01/2023","durée":13,"date de fin":"10/18/2022","taux de base":4.22,"discount":0.46,"taux bonifié":2.99,"condition (GWh/an)":3.846,"condition (tCO2/an)":3.44,"dernière date d'observation":"11/7/2022","réalisation (GWh)":190.1,"réalisation (tCO2)":62.86},
{"entreprise":"Skilith","secteur d'activité":"Finance","ville":"Cochrane","région":93,"date de l'emprunt":"08/05/2021","durée":16,"date de fin":"11/21/2022","taux de base":2.65,"discount":0.26,"taux bonifié":3.08,"condition (GWh/an)":2.392,"condition (tCO2/an)":6.3,"dernière date d'observation":"3/25/2022","réalisation (GWh)":39.86,"réalisation (tCO2)":108.36},
{"entreprise":"Izio","secteur d'activité":"Consumer Services","ville":"Nanmo","région":11,"date de l'emprunt":"13/02/2022","durée":16,"date de fin":"6/25/2022","taux de base":5.0,"discount":0.3,"taux bonifié":3.72,"condition (GWh/an)":4.741,"condition (tCO2/an)":170.67,"dernière date d'observation":"7/1/2022","réalisation (GWh)":125.65,"réalisation (tCO2)":140.65},
{"entreprise":"Kazu","secteur d'activité":"Health Care","ville":"Ust’-Labinsk","région":84,"date de l'emprunt":"27/08/2022","durée":15,"date de fin":"11/9/2022","taux de base":3.59,"discount":0.92,"taux bonifié":2.66,"condition (GWh/an)":0.272,"condition (tCO2/an)":112.44,"dernière date d'observation":"11/6/2022","réalisation (GWh)":179.21,"réalisation (tCO2)":78.5},
{"entreprise":"Tagchat","secteur d'activité":"Finance","ville":"Västra Frölunda","région":63,"date de l'emprunt":"13/11/2022","durée":2,"date de fin":"12/13/2022","taux de base":2.22,"discount":0.56,"taux bonifié":5.18,"condition (GWh/an)":1.726,"condition (tCO2/an)":34.6,"dernière date d'observation":"1/19/2023","réalisation (GWh)":21.7,"réalisation (tCO2)":196.22},
{"entreprise":"Yodel","secteur d'activité":"Consumer Services","ville":"Yelets","région":54,"date de l'emprunt":"22/06/2022","durée":20,"date de fin":"10/10/2022","taux de base":3.34,"discount":0.46,"taux bonifié":2.74,"condition (GWh/an)":0.224,"condition (tCO2/an)":39.81,"dernière date d'observation":"6/25/2022","réalisation (GWh)":187.62,"réalisation (tCO2)":48.99},
{"entreprise":"Youtags","secteur d'activité":"Finance","ville":"Wangda","région":95,"date de l'emprunt":"11/08/2020","durée":10,"date de fin":"6/2/2022","taux de base":2.55,"discount":0.17,"taux bonifié":4.29,"condition (GWh/an)":1.736,"condition (tCO2/an)":187.42,"dernière date d'observation":"10/13/2022","réalisation (GWh)":91.91,"réalisation (tCO2)":95.13},
{"entreprise":"Topicshots","secteur d'activité":"n/a","ville":"Castêlo","région":72,"date de l'emprunt":"28/01/2020","durée":6,"date de fin":"5/30/2022","taux de base":5.84,"discount":0.56,"taux bonifié":3.12,"condition (GWh/an)":0.094,"condition (tCO2/an)":78.99,"dernière date d'observation":"3/15/2022","réalisation (GWh)":67.94,"réalisation (tCO2)":54.75},
{"entreprise":"Flashdog","secteur d'activité":"Finance","ville":"Bayt ‘Awwā","région":42,"date de l'emprunt":"26/06/2021","durée":3,"date de fin":"1/22/2023","taux de base":3.27,"discount":0.58,"taux bonifié":4.78,"condition (GWh/an)":2.919,"condition (tCO2/an)":132.93,"dernière date d'observation":"10/20/2022","réalisation (GWh)":56.89,"réalisation (tCO2)":186.23},
{"entreprise":"Eire","secteur d'activité":"Technology","ville":"Peñarrubia","région":90,"date de l'emprunt":"02/04/2021","durée":17,"date de fin":"4/5/2022","taux de base":3.69,"discount":0.93,"taux bonifié":5.37,"condition (GWh/an)":3.742,"condition (tCO2/an)":40.58,"dernière date d'observation":"9/3/2022","réalisation (GWh)":160.66,"réalisation (tCO2)":141.75},
{"entreprise":"Skimia","secteur d'activité":"Finance","ville":"Bielawa","région":69,"date de l'emprunt":"12/10/2021","durée":20,"date de fin":"7/31/2022","taux de base":3.77,"discount":0.49,"taux bonifié":2.44,"condition (GWh/an)":1.578,"condition (tCO2/an)":174.87,"dernière date d'observation":"7/13/2022","réalisation (GWh)":143.19,"réalisation (tCO2)":101.03},
{"entreprise":"Centizu","secteur d'activité":"Finance","ville":"Grand Bois","région":75,"date de l'emprunt":"15/10/2022","durée":3,"date de fin":"5/17/2022","taux de base":4.63,"discount":0.11,"taux bonifié":4.6,"condition (GWh/an)":1.224,"condition (tCO2/an)":195.77,"dernière date d'observation":"6/20/2022","réalisation (GWh)":67.78,"réalisation (tCO2)":196.37},
{"entreprise":"Yambee","secteur d'activité":"Technology","ville":"Wangzuo","région":82,"date de l'emprunt":"25/02/2020","durée":18,"date de fin":"7/17/2022","taux de base":2.89,"discount":0.7,"taux bonifié":5.55,"condition (GWh/an)":2.208,"condition (tCO2/an)":125.5,"dernière date d'observation":"12/29/2022","réalisation (GWh)":26.52,"réalisation (tCO2)":197.11},
{"entreprise":"Skyvu","secteur d'activité":"Health Care","ville":"Changfeng","région":93,"date de l'emprunt":"15/01/2020","durée":9,"date de fin":"10/6/2022","taux de base":5.3,"discount":0.93,"taux bonifié":2.17,"condition (GWh/an)":2.777,"condition (tCO2/an)":77.09,"dernière date d'observation":"3/21/2022","réalisation (GWh)":110.93,"réalisation (tCO2)":131.71},
{"entreprise":"Tagpad","secteur d'activité":"Consumer Services","ville":"Uppsala","région":19,"date de l'emprunt":"20/04/2021","durée":14,"date de fin":"7/19/2022","taux de base":4.73,"discount":0.81,"taux bonifié":5.86,"condition (GWh/an)":3.222,"condition (tCO2/an)":119.17,"dernière date d'observation":"4/28/2022","réalisation (GWh)":186.66,"réalisation (tCO2)":63.5},
{"entreprise":"Innotype","secteur d'activité":"Technology","ville":"Solna","région":17,"date de l'emprunt":"30/04/2021","durée":15,"date de fin":"2/26/2022","taux de base":5.49,"discount":0.45,"taux bonifié":4.5,"condition (GWh/an)":3.934,"condition (tCO2/an)":95.14,"dernière date d'observation":"8/19/2022","réalisation (GWh)":93.26,"réalisation (tCO2)":166.5},
{"entreprise":"Browsedrive","secteur d'activité":"Health Care","ville":"Ulan Hua","région":34,"date de l'emprunt":"03/11/2022","durée":7,"date de fin":"10/21/2022","taux de base":5.76,"discount":0.13,"taux bonifié":4.29,"condition (GWh/an)":0.118,"condition (tCO2/an)":12.99,"dernière date d'observation":"10/9/2022","réalisation (GWh)":50.27,"réalisation (tCO2)":154.35},
{"entreprise":"Miboo","secteur d'activité":"Public Utilities","ville":"San Benito Abad","région":5,"date de l'emprunt":"10/12/2020","durée":4,"date de fin":"1/28/2023","taux de base":5.23,"discount":0.86,"taux bonifié":3.39,"condition (GWh/an)":4.303,"condition (tCO2/an)":122.02,"dernière date d'observation":"5/21/2022","réalisation (GWh)":14.94,"réalisation (tCO2)":29.44},
{"entreprise":"Zoombeat","secteur d'activité":"Energy","ville":"Daixi","région":57,"date de l'emprunt":"24/03/2020","durée":10,"date de fin":"8/28/2022","taux de base":4.61,"discount":0.22,"taux bonifié":2.57,"condition (GWh/an)":0.904,"condition (tCO2/an)":68.94,"dernière date d'observation":"2/28/2022","réalisation (GWh)":57.52,"réalisation (tCO2)":165.18},
{"entreprise":"Divavu","secteur d'activité":"Energy","ville":"Xinshi","région":49,"date de l'emprunt":"12/01/2021","durée":3,"date de fin":"3/8/2022","taux de base":2.52,"discount":0.56,"taux bonifié":5.85,"condition (GWh/an)":1.682,"condition (tCO2/an)":33.52,"dernière date d'observation":"11/5/2022","réalisation (GWh)":74.55,"réalisation (tCO2)":146.16},
{"entreprise":"Buzzdog","secteur d'activité":"Consumer Non-Durables","ville":"Zhuoshui","région":84,"date de l'emprunt":"09/11/2020","durée":16,"date de fin":"5/8/2022","taux de base":5.17,"discount":0.94,"taux bonifié":5.16,"condition (GWh/an)":1.307,"condition (tCO2/an)":123.14,"dernière date d'observation":"3/11/2022","réalisation (GWh)":92.5,"réalisation (tCO2)":8.21},
{"entreprise":"Devcast","secteur d'activité":"Consumer Services","ville":"Solntsevo","région":21,"date de l'emprunt":"30/07/2021","durée":19,"date de fin":"3/1/2022","taux de base":5.5,"discount":0.05,"taux bonifié":5.88,"condition (GWh/an)":2.795,"condition (tCO2/an)":64.65,"dernière date d'observation":"5/26/2022","réalisation (GWh)":170.39,"réalisation (tCO2)":137.43},
{"entreprise":"Vimbo","secteur d'activité":"n/a","ville":"Aucallama","région":42,"date de l'emprunt":"06/12/2022","durée":5,"date de fin":"6/7/2022","taux de base":5.3,"discount":0.29,"taux bonifié":4.0,"condition (GWh/an)":4.289,"condition (tCO2/an)":115.71,"dernière date d'observation":"3/29/2022","réalisation (GWh)":27.49,"réalisation (tCO2)":195.66},
{"entreprise":"Skajo","secteur d'activité":"Capital Goods","ville":"Manamrag","région":38,"date de l'emprunt":"28/03/2022","durée":12,"date de fin":"3/12/2022","taux de base":4.93,"discount":0.44,"taux bonifié":5.93,"condition (GWh/an)":5.305,"condition (tCO2/an)":23.82,"dernière date d'observation":"5/13/2022","réalisation (GWh)":48.46,"réalisation (tCO2)":190.17},
{"entreprise":"Realbridge","secteur d'activité":"n/a","ville":"London","région":92,"date de l'emprunt":"17/10/2021","durée":19,"date de fin":"5/14/2022","taux de base":2.27,"discount":0.93,"taux bonifié":2.55,"condition (GWh/an)":1.911,"condition (tCO2/an)":161.8,"dernière date d'observation":"10/30/2022","réalisation (GWh)":42.57,"réalisation (tCO2)":152.58},
{"entreprise":"Innojam","secteur d'activité":"Finance","ville":"Vilque Chico","région":95,"date de l'emprunt":"01/05/2022","durée":14,"date de fin":"5/1/2022","taux de base":3.04,"discount":0.05,"taux bonifié":3.9,"condition (GWh/an)":5.273,"condition (tCO2/an)":120.67,"dernière date d'observation":"11/3/2022","réalisation (GWh)":78.58,"réalisation (tCO2)":190.53},
{"entreprise":"Camimbo","secteur d'activité":"Finance","ville":"Téra","région":47,"date de l'emprunt":"13/02/2023","durée":19,"date de fin":"9/24/2022","taux de base":5.45,"discount":0.7,"taux bonifié":3.34,"condition (GWh/an)":5.735,"condition (tCO2/an)":90.22,"dernière date d'observation":"7/2/2022","réalisation (GWh)":123.49,"réalisation (tCO2)":124.85},
{"entreprise":"Oyoyo","secteur d'activité":"n/a","ville":"Chimoio","région":48,"date de l'emprunt":"04/04/2020","durée":8,"date de fin":"11/7/2022","taux de base":4.93,"discount":0.59,"taux bonifié":5.75,"condition (GWh/an)":1.06,"condition (tCO2/an)":71.39,"dernière date d'observation":"4/18/2022","réalisation (GWh)":3.2,"réalisation (tCO2)":64.95},
{"entreprise":"Yamia","secteur d'activité":"n/a","ville":"Baijiang","région":70,"date de l'emprunt":"19/05/2021","durée":6,"date de fin":"2/7/2023","taux de base":4.24,"discount":0.59,"taux bonifié":3.31,"condition (GWh/an)":3.535,"condition (tCO2/an)":153.76,"dernière date d'observation":"4/24/2022","réalisation (GWh)":25.44,"réalisation (tCO2)":135.96},
{"entreprise":"Brainsphere","secteur d'activité":"Energy","ville":"Ourozinho","région":6,"date de l'emprunt":"13/08/2020","durée":20,"date de fin":"5/23/2022","taux de base":2.89,"discount":0.27,"taux bonifié":4.52,"condition (GWh/an)":0.029,"condition (tCO2/an)":170.65,"dernière date d'observation":"10/24/2022","réalisation (GWh)":53.76,"réalisation (tCO2)":22.45},
{"entreprise":"JumpXS","secteur d'activité":"Consumer Services","ville":"Książki","région":12,"date de l'emprunt":"03/07/2021","durée":10,"date de fin":"4/25/2022","taux de base":5.07,"discount":0.58,"taux bonifié":5.16,"condition (GWh/an)":0.366,"condition (tCO2/an)":11.7,"dernière date d'observation":"10/31/2022","réalisation (GWh)":155.62,"réalisation (tCO2)":105.01},
{"entreprise":"Flipstorm","secteur d'activité":"Health Care","ville":"Kukës","région":94,"date de l'emprunt":"04/09/2022","durée":5,"date de fin":"12/20/2022","taux de base":5.47,"discount":0.99,"taux bonifié":3.45,"condition (GWh/an)":2.334,"condition (tCO2/an)":151.56,"dernière date d'observation":"9/14/2022","réalisation (GWh)":38.72,"réalisation (tCO2)":24.89},
{"entreprise":"Skippad","secteur d'activité":"Consumer Services","ville":"Thuận Nam","région":87,"date de l'emprunt":"29/03/2020","durée":5,"date de fin":"5/24/2022","taux de base":4.6,"discount":0.87,"taux bonifié":3.0,"condition (GWh/an)":4.895,"condition (tCO2/an)":51.26,"dernière date d'observation":"8/23/2022","réalisation (GWh)":50.64,"réalisation (tCO2)":94.8},
{"entreprise":"Blognation","secteur d'activité":"Consumer Services","ville":"Rakszawa","région":21,"date de l'emprunt":"02/07/2021","durée":16,"date de fin":"4/24/2022","taux de base":5.94,"discount":0.6,"taux bonifié":2.9,"condition (GWh/an)":2.116,"condition (tCO2/an)":186.39,"dernière date d'observation":"2/22/2022","réalisation (GWh)":179.91,"réalisation (tCO2)":8.52},
{"entreprise":"Feedbug","secteur d'activité":"n/a","ville":"Duy Xuyên","région":12,"date de l'emprunt":"19/04/2021","durée":20,"date de fin":"4/3/2022","taux de base":5.26,"discount":0.39,"taux bonifié":5.22,"condition (GWh/an)":5.581,"condition (tCO2/an)":166.28,"dernière date d'observation":"2/3/2023","réalisation (GWh)":119.49,"réalisation (tCO2)":178.3},
{"entreprise":"Dabjam","secteur d'activité":"Basic Industries","ville":"Heřmanova Huť","région":61,"date de l'emprunt":"14/12/2021","durée":20,"date de fin":"4/23/2022","taux de base":5.84,"discount":0.33,"taux bonifié":4.59,"condition (GWh/an)":0.396,"condition (tCO2/an)":120.29,"dernière date d'observation":"5/19/2022","réalisation (GWh)":124.69,"réalisation (tCO2)":55.48},
{"entreprise":"Quire","secteur d'activité":"Finance","ville":"Silgueiros","région":14,"date de l'emprunt":"04/07/2022","durée":13,"date de fin":"5/9/2022","taux de base":5.98,"discount":0.49,"taux bonifié":3.54,"condition (GWh/an)":4.249,"condition (tCO2/an)":38.9,"dernière date d'observation":"7/28/2022","réalisation (GWh)":64.5,"réalisation (tCO2)":37.55},
{"entreprise":"Jabberstorm","secteur d'activité":"n/a","ville":"Kangin","région":25,"date de l'emprunt":"26/10/2020","durée":4,"date de fin":"3/19/2022","taux de base":3.3,"discount":0.58,"taux bonifié":4.86,"condition (GWh/an)":0.758,"condition (tCO2/an)":135.28,"dernière date d'observation":"4/30/2022","réalisation (GWh)":126.55,"réalisation (tCO2)":149.38},
{"entreprise":"Babblestorm","secteur d'activité":"n/a","ville":"Dū Laīnah","région":56,"date de l'emprunt":"30/07/2021","durée":2,"date de fin":"10/10/2022","taux de base":4.21,"discount":0.35,"taux bonifié":3.96,"condition (GWh/an)":3.968,"condition (tCO2/an)":59.28,"dernière date d'observation":"6/9/2022","réalisation (GWh)":122.67,"réalisation (tCO2)":181.06},
{"entreprise":"Wordify","secteur d'activité":"Energy","ville":"Heshui","région":70,"date de l'emprunt":"19/11/2022","durée":20,"date de fin":"3/27/2022","taux de base":3.78,"discount":0.73,"taux bonifié":2.25,"condition (GWh/an)":3.564,"condition (tCO2/an)":198.02,"dernière date d'observation":"9/18/2022","réalisation (GWh)":157.23,"réalisation (tCO2)":195.17},
{"entreprise":"Babbleset","secteur d'activité":"n/a","ville":"Ntoke","région":62,"date de l'emprunt":"28/11/2022","durée":14,"date de fin":"2/16/2022","taux de base":3.9,"discount":0.28,"taux bonifié":2.63,"condition (GWh/an)":3.743,"condition (tCO2/an)":132.08,"dernière date d'observation":"9/1/2022","réalisation (GWh)":78.41,"réalisation (tCO2)":17.07},
{"entreprise":"Gabcube","secteur d'activité":"n/a","ville":"Meilong","région":10,"date de l'emprunt":"03/11/2021","durée":8,"date de fin":"12/15/2022","taux de base":5.1,"discount":0.61,"taux bonifié":2.84,"condition (GWh/an)":0.839,"condition (tCO2/an)":94.4,"dernière date d'observation":"12/23/2022","réalisation (GWh)":6.74,"réalisation (tCO2)":52.43},
{"entreprise":"Thoughtstorm","secteur d'activité":"Capital Goods","ville":"Borlänge","région":91,"date de l'emprunt":"05/08/2020","durée":9,"date de fin":"2/9/2023","taux de base":3.07,"discount":0.7,"taux bonifié":4.66,"condition (GWh/an)":2.453,"condition (tCO2/an)":100.53,"dernière date d'observation":"2/19/2022","réalisation (GWh)":8.03,"réalisation (tCO2)":122.26},
{"entreprise":"Browsedrive","secteur d'activité":"Technology","ville":"Santo Amaro","région":46,"date de l'emprunt":"01/01/2021","durée":11,"date de fin":"2/10/2023","taux de base":4.03,"discount":0.41,"taux bonifié":4.81,"condition (GWh/an)":3.819,"condition (tCO2/an)":53.46,"dernière date d'observation":"6/2/2022","réalisation (GWh)":78.89,"réalisation (tCO2)":89.68},
{"entreprise":"Edgetag","secteur d'activité":"Consumer Services","ville":"Odivelas","région":36,"date de l'emprunt":"27/08/2022","durée":12,"date de fin":"2/26/2022","taux de base":5.09,"discount":0.09,"taux bonifié":3.93,"condition (GWh/an)":3.648,"condition (tCO2/an)":105.39,"dernière date d'observation":"1/6/2023","réalisation (GWh)":53.86,"réalisation (tCO2)":172.69},
{"entreprise":"Dynabox","secteur d'activité":"Capital Goods","ville":"Thị Trấn Nước Hai","région":33,"date de l'emprunt":"27/09/2020","durée":2,"date de fin":"1/8/2023","taux de base":2.24,"discount":0.29,"taux bonifié":4.48,"condition (GWh/an)":1.105,"condition (tCO2/an)":190.18,"dernière date d'observation":"5/6/2022","réalisation (GWh)":73.26,"réalisation (tCO2)":155.95},
{"entreprise":"Dabshots","secteur d'activité":"n/a","ville":"Magisterial","région":60,"date de l'emprunt":"06/12/2022","durée":2,"date de fin":"12/29/2022","taux de base":4.77,"discount":0.55,"taux bonifié":4.07,"condition (GWh/an)":2.066,"condition (tCO2/an)":6.06,"dernière date d'observation":"3/22/2022","réalisation (GWh)":36.81,"réalisation (tCO2)":150.02},
{"entreprise":"Quinu","secteur d'activité":"Capital Goods","ville":"Plottier","région":88,"date de l'emprunt":"28/02/2021","durée":15,"date de fin":"11/27/2022","taux de base":3.42,"discount":0.69,"taux bonifié":3.56,"condition (GWh/an)":0.321,"condition (tCO2/an)":191.83,"dernière date d'observation":"6/20/2022","réalisation (GWh)":151.51,"réalisation (tCO2)":55.06},
{"entreprise":"Oyonder","secteur d'activité":"Basic Industries","ville":"Canmore","région":70,"date de l'emprunt":"16/12/2020","durée":14,"date de fin":"9/13/2022","taux de base":3.82,"discount":0.91,"taux bonifié":3.9,"condition (GWh/an)":1.74,"condition (tCO2/an)":139.35,"dernière date d'observation":"7/10/2022","réalisation (GWh)":60.52,"réalisation (tCO2)":132.97},
{"entreprise":"Aimbo","secteur d'activité":"n/a","ville":"Dhali","région":53,"date de l'emprunt":"03/08/2020","durée":20,"date de fin":"6/27/2022","taux de base":3.14,"discount":0.43,"taux bonifié":3.47,"condition (GWh/an)":0.975,"condition (tCO2/an)":188.65,"dernière date d'observation":"2/18/2022","réalisation (GWh)":51.93,"réalisation (tCO2)":80.1},
{"entreprise":"Abatz","secteur d'activité":"Finance","ville":"Pangpang","région":46,"date de l'emprunt":"13/12/2020","durée":8,"date de fin":"7/6/2022","taux de base":2.87,"discount":0.34,"taux bonifié":3.4,"condition (GWh/an)":4.531,"condition (tCO2/an)":148.0,"dernière date d'observation":"3/22/2022","réalisation (GWh)":154.1,"réalisation (tCO2)":115.38},
{"entreprise":"Tagfeed","secteur d'activité":"n/a","ville":"Phong Điền","région":68,"date de l'emprunt":"25/06/2022","durée":18,"date de fin":"1/31/2023","taux de base":3.2,"discount":0.37,"taux bonifié":5.12,"condition (GWh/an)":3.475,"condition (tCO2/an)":132.01,"dernière date d'observation":"1/27/2023","réalisation (GWh)":177.69,"réalisation (tCO2)":197.32},
{"entreprise":"Fanoodle","secteur d'activité":"Consumer Services","ville":"Nāḩiyat Hīrān","région":23,"date de l'emprunt":"29/01/2020","durée":12,"date de fin":"12/3/2022","taux de base":4.04,"discount":0.49,"taux bonifié":2.04,"condition (GWh/an)":0.5,"condition (tCO2/an)":133.54,"dernière date d'observation":"5/17/2022","réalisation (GWh)":198.5,"réalisation (tCO2)":53.17},
{"entreprise":"Skyvu","secteur d'activité":"Health Care","ville":"Rogowo","région":36,"date de l'emprunt":"18/12/2020","durée":13,"date de fin":"9/22/2022","taux de base":5.1,"discount":0.1,"taux bonifié":2.79,"condition (GWh/an)":3.757,"condition (tCO2/an)":24.19,"dernière date d'observation":"1/19/2023","réalisation (GWh)":184.29,"réalisation (tCO2)":77.64},
{"entreprise":"Quimm","secteur d'activité":"Finance","ville":"Grodków","région":19,"date de l'emprunt":"14/12/2022","durée":12,"date de fin":"3/25/2022","taux de base":3.65,"discount":0.04,"taux bonifié":2.34,"condition (GWh/an)":4.255,"condition (tCO2/an)":141.91,"dernière date d'observation":"10/17/2022","réalisation (GWh)":43.1,"réalisation (tCO2)":166.78},
{"entreprise":"Flipbug","secteur d'activité":"Public Utilities","ville":"Três Corações","région":23,"date de l'emprunt":"30/01/2021","durée":13,"date de fin":"12/14/2022","taux de base":5.1,"discount":0.92,"taux bonifié":3.03,"condition (GWh/an)":4.572,"condition (tCO2/an)":92.11,"dernière date d'observation":"2/17/2022","réalisation (GWh)":56.88,"réalisation (tCO2)":9.81},
{"entreprise":"Tagpad","secteur d'activité":"n/a","ville":"Jagabaya Dua","région":5,"date de l'emprunt":"26/12/2021","durée":6,"date de fin":"9/12/2022","taux de base":2.28,"discount":0.26,"taux bonifié":3.98,"condition (GWh/an)":3.015,"condition (tCO2/an)":120.0,"dernière date d'observation":"3/3/2022","réalisation (GWh)":31.34,"réalisation (tCO2)":141.57},
{"entreprise":"Quamba","secteur d'activité":"Consumer Services","ville":"Balatun","région":19,"date de l'emprunt":"15/06/2021","durée":3,"date de fin":"6/3/2022","taux de base":4.15,"discount":0.41,"taux bonifié":3.46,"condition (GWh/an)":1.119,"condition (tCO2/an)":114.06,"dernière date d'observation":"8/16/2022","réalisation (GWh)":124.35,"réalisation (tCO2)":52.65},
{"entreprise":"Aimbo","secteur d'activité":"Finance","ville":"Triteh","région":54,"date de l'emprunt":"28/03/2020","durée":13,"date de fin":"5/11/2022","taux de base":3.0,"discount":0.34,"taux bonifié":4.58,"condition (GWh/an)":2.895,"condition (tCO2/an)":69.45,"dernière date d'observation":"1/14/2023","réalisation (GWh)":142.14,"réalisation (tCO2)":84.25},
{"entreprise":"Kamba","secteur d'activité":"Consumer Durables","ville":"Zhongben","région":18,"date de l'emprunt":"04/06/2020","durée":16,"date de fin":"2/7/2023","taux de base":2.29,"discount":0.55,"taux bonifié":5.82,"condition (GWh/an)":2.141,"condition (tCO2/an)":81.33,"dernière date d'observation":"8/23/2022","réalisation (GWh)":3.48,"réalisation (tCO2)":140.17},
{"entreprise":"Blogpad","secteur d'activité":"Health Care","ville":"Šabac","région":27,"date de l'emprunt":"02/12/2020","durée":4,"date de fin":"11/19/2022","taux de base":3.93,"discount":0.42,"taux bonifié":3.82,"condition (GWh/an)":5.084,"condition (tCO2/an)":134.77,"dernière date d'observation":"9/20/2022","réalisation (GWh)":142.61,"réalisation (tCO2)":161.55},
{"entreprise":"Livepath","secteur d'activité":"n/a","ville":"San Fabian","région":80,"date de l'emprunt":"18/06/2020","durée":2,"date de fin":"9/1/2022","taux de base":3.33,"discount":0.03,"taux bonifié":3.48,"condition (GWh/an)":0.273,"condition (tCO2/an)":114.22,"dernière date d'observation":"1/19/2023","réalisation (GWh)":100.47,"réalisation (tCO2)":35.0},
{"entreprise":"Zoomdog","secteur d'activité":"Technology","ville":"Independencia","région":49,"date de l'emprunt":"23/04/2022","durée":20,"date de fin":"2/12/2023","taux de base":5.22,"discount":0.03,"taux bonifié":4.35,"condition (GWh/an)":3.963,"condition (tCO2/an)":90.54,"dernière date d'observation":"3/21/2022","réalisation (GWh)":65.23,"réalisation (tCO2)":99.64},
{"entreprise":"Wikibox","secteur d'activité":"Energy","ville":"Trudobelikovskiy","région":87,"date de l'emprunt":"09/11/2020","durée":14,"date de fin":"6/14/2022","taux de base":4.66,"discount":0.39,"taux bonifié":2.35,"condition (GWh/an)":2.85,"condition (tCO2/an)":132.66,"dernière date d'observation":"2/17/2022","réalisation (GWh)":51.19,"réalisation (tCO2)":45.33},
{"entreprise":"Jaxspan","secteur d'activité":"Consumer Services","ville":"Calvaria de Baixo","région":83,"date de l'emprunt":"16/08/2022","durée":9,"date de fin":"10/26/2022","taux de base":3.41,"discount":0.75,"taux bonifié":3.7,"condition (GWh/an)":3.163,"condition (tCO2/an)":139.98,"dernière date d'observation":"11/18/2022","réalisation (GWh)":11.1,"réalisation (tCO2)":94.21},
{"entreprise":"Kazu","secteur d'activité":"Basic Industries","ville":"Montgomery","région":70,"date de l'emprunt":"13/07/2021","durée":3,"date de fin":"4/7/2022","taux de base":5.44,"discount":0.41,"taux bonifié":2.99,"condition (GWh/an)":2.226,"condition (tCO2/an)":177.14,"dernière date d'observation":"2/7/2023","réalisation (GWh)":67.82,"réalisation (tCO2)":77.89},
{"entreprise":"Browsedrive","secteur d'activité":"Finance","ville":"Comal","région":48,"date de l'emprunt":"17/03/2022","durée":8,"date de fin":"4/18/2022","taux de base":3.82,"discount":0.13,"taux bonifié":2.68,"condition (GWh/an)":0.202,"condition (tCO2/an)":26.37,"dernière date d'observation":"10/26/2022","réalisation (GWh)":17.71,"réalisation (tCO2)":85.63},
{"entreprise":"Zoozzy","secteur d'activité":"Energy","ville":"Argithéa","région":44,"date de l'emprunt":"10/12/2021","durée":18,"date de fin":"12/24/2022","taux de base":2.61,"discount":0.3,"taux bonifié":5.05,"condition (GWh/an)":1.858,"condition (tCO2/an)":125.99,"dernière date d'observation":"12/20/2022","réalisation (GWh)":35.94,"réalisation (tCO2)":145.12},
{"entreprise":"Feednation","secteur d'activité":"Finance","ville":"Asan","région":77,"date de l'emprunt":"10/01/2020","durée":16,"date de fin":"7/1/2022","taux de base":4.28,"discount":0.72,"taux bonifié":3.09,"condition (GWh/an)":4.403,"condition (tCO2/an)":102.81,"dernière date d'observation":"1/16/2023","réalisation (GWh)":99.16,"réalisation (tCO2)":51.92},
{"entreprise":"Linkbridge","secteur d'activité":"Consumer Services","ville":"Bazhu","région":51,"date de l'emprunt":"26/03/2022","durée":8,"date de fin":"9/29/2022","taux de base":3.39,"discount":0.05,"taux bonifié":4.75,"condition (GWh/an)":2.295,"condition (tCO2/an)":198.48,"dernière date d'observation":"5/13/2022","réalisation (GWh)":48.99,"réalisation (tCO2)":52.88},
{"entreprise":"Feedfire","secteur d'activité":"n/a","ville":"Wuchagou","région":84,"date de l'emprunt":"26/03/2022","durée":18,"date de fin":"9/9/2022","taux de base":5.04,"discount":0.43,"taux bonifié":3.53,"condition (GWh/an)":2.81,"condition (tCO2/an)":86.39,"dernière date d'observation":"10/10/2022","réalisation (GWh)":57.75,"réalisation (tCO2)":76.32},
{"entreprise":"Meeveo","secteur d'activité":"Transportation","ville":"Ulster Spring","région":15,"date de l'emprunt":"13/08/2022","durée":10,"date de fin":"1/1/2023","taux de base":3.53,"discount":0.31,"taux bonifié":3.2,"condition (GWh/an)":2.064,"condition (tCO2/an)":102.71,"dernière date d'observation":"9/4/2022","réalisation (GWh)":5.7,"réalisation (tCO2)":159.29},
{"entreprise":"Abata","secteur d'activité":"Finance","ville":"Jinchuan","région":91,"date de l'emprunt":"23/05/2022","durée":8,"date de fin":"5/26/2022","taux de base":2.45,"discount":0.03,"taux bonifié":4.12,"condition (GWh/an)":1.258,"condition (tCO2/an)":189.44,"dernière date d'observation":"10/25/2022","réalisation (GWh)":189.81,"réalisation (tCO2)":10.66},
{"entreprise":"Yamia","secteur d'activité":"Consumer Non-Durables","ville":"Oujiangcha","région":19,"date de l'emprunt":"26/03/2022","durée":12,"date de fin":"12/7/2022","taux de base":5.73,"discount":0.33,"taux bonifié":4.81,"condition (GWh/an)":5.704,"condition (tCO2/an)":28.86,"dernière date d'observation":"1/13/2023","réalisation (GWh)":58.55,"réalisation (tCO2)":2.37},
{"entreprise":"Yotz","secteur d'activité":"Public Utilities","ville":"Agiásos","région":1,"date de l'emprunt":"11/05/2021","durée":19,"date de fin":"11/24/2022","taux de base":3.72,"discount":0.06,"taux bonifié":2.45,"condition (GWh/an)":3.071,"condition (tCO2/an)":10.26,"dernière date d'observation":"10/19/2022","réalisation (GWh)":6.13,"réalisation (tCO2)":109.3},
{"entreprise":"Innotype","secteur d'activité":"n/a","ville":"Tagakpan","région":83,"date de l'emprunt":"25/11/2020","durée":3,"date de fin":"2/15/2022","taux de base":3.71,"discount":0.47,"taux bonifié":5.6,"condition (GWh/an)":1.686,"condition (tCO2/an)":71.77,"dernière date d'observation":"11/9/2022","réalisation (GWh)":94.39,"réalisation (tCO2)":157.63},
{"entreprise":"Tazz","secteur d'activité":"Consumer Services","ville":"Danderyd","région":5,"date de l'emprunt":"09/03/2020","durée":10,"date de fin":"11/9/2022","taux de base":3.36,"discount":0.54,"taux bonifié":3.65,"condition (GWh/an)":2.081,"condition (tCO2/an)":140.29,"dernière date d'observation":"12/29/2022","réalisation (GWh)":192.94,"réalisation (tCO2)":163.01},
{"entreprise":"Skivee","secteur d'activité":"Finance","ville":"Ad Dawḩah","région":24,"date de l'emprunt":"09/07/2020","durée":16,"date de fin":"10/23/2022","taux de base":4.09,"discount":0.14,"taux bonifié":3.94,"condition (GWh/an)":1.331,"condition (tCO2/an)":30.48,"dernière date d'observation":"10/11/2022","réalisation (GWh)":188.29,"réalisation (tCO2)":95.33},
{"entreprise":"Cogidoo","secteur d'activité":"Technology","ville":"‘Izrā","région":86,"date de l'emprunt":"24/12/2020","durée":4,"date de fin":"5/17/2022","taux de base":4.14,"discount":0.77,"taux bonifié":3.2,"condition (GWh/an)":2.596,"condition (tCO2/an)":109.86,"dernière date d'observation":"12/3/2022","réalisation (GWh)":150.85,"réalisation (tCO2)":188.2},
{"entreprise":"Shuffledrive","secteur d'activité":"n/a","ville":"El Corpus","région":88,"date de l'emprunt":"11/05/2021","durée":19,"date de fin":"2/11/2023","taux de base":2.43,"discount":0.6,"taux bonifié":3.57,"condition (GWh/an)":0.93,"condition (tCO2/an)":180.89,"dernière date d'observation":"8/2/2022","réalisation (GWh)":154.27,"réalisation (tCO2)":176.34},
{"entreprise":"Skinder","secteur d'activité":"Technology","ville":"Figueira","région":4,"date de l'emprunt":"18/08/2020","durée":15,"date de fin":"7/12/2022","taux de base":5.05,"discount":0.05,"taux bonifié":2.74,"condition (GWh/an)":3.378,"condition (tCO2/an)":181.81,"dernière date d'observation":"9/27/2022","réalisation (GWh)":129.78,"réalisation (tCO2)":148.24},
{"entreprise":"Plajo","secteur d'activité":"Capital Goods","ville":"Kuala Terengganu","région":12,"date de l'emprunt":"09/12/2021","durée":18,"date de fin":"10/4/2022","taux de base":3.43,"discount":0.59,"taux bonifié":3.06,"condition (GWh/an)":2.439,"condition (tCO2/an)":153.65,"dernière date d'observation":"8/26/2022","réalisation (GWh)":15.36,"réalisation (tCO2)":65.21},
{"entreprise":"Thoughtstorm","secteur d'activité":"n/a","ville":"Maputsoe","région":40,"date de l'emprunt":"31/05/2021","durée":9,"date de fin":"9/23/2022","taux de base":4.73,"discount":0.15,"taux bonifié":4.66,"condition (GWh/an)":4.996,"condition (tCO2/an)":104.85,"dernière date d'observation":"11/29/2022","réalisation (GWh)":52.34,"réalisation (tCO2)":112.58},
{"entreprise":"Muxo","secteur d'activité":"Health Care","ville":"Neuss","région":55,"date de l'emprunt":"04/09/2022","durée":13,"date de fin":"8/27/2022","taux de base":2.33,"discount":0.34,"taux bonifié":5.82,"condition (GWh/an)":5.585,"condition (tCO2/an)":20.12,"dernière date d'observation":"7/2/2022","réalisation (GWh)":179.98,"réalisation (tCO2)":118.24},
{"entreprise":"Feedbug","secteur d'activité":"Finance","ville":"Opuwo","région":52,"date de l'emprunt":"20/05/2022","durée":12,"date de fin":"7/22/2022","taux de base":3.99,"discount":0.93,"taux bonifié":2.17,"condition (GWh/an)":2.302,"condition (tCO2/an)":119.81,"dernière date d'observation":"10/27/2022","réalisation (GWh)":183.96,"réalisation (tCO2)":165.13},
{"entreprise":"Myworks","secteur d'activité":"Consumer Services","ville":"El Triunfo","région":29,"date de l'emprunt":"01/09/2020","durée":6,"date de fin":"3/9/2022","taux de base":2.14,"discount":0.36,"taux bonifié":3.36,"condition (GWh/an)":2.249,"condition (tCO2/an)":60.27,"dernière date d'observation":"4/25/2022","réalisation (GWh)":65.45,"réalisation (tCO2)":196.48},
{"entreprise":"Voomm","secteur d'activité":"Health Care","ville":"Macabugos","région":33,"date de l'emprunt":"15/10/2020","durée":7,"date de fin":"9/16/2022","taux de base":2.86,"discount":0.79,"taux bonifié":4.14,"condition (GWh/an)":3.976,"condition (tCO2/an)":43.76,"dernière date d'observation":"9/4/2022","réalisation (GWh)":3.36,"réalisation (tCO2)":135.1},
{"entreprise":"Leexo","secteur d'activité":"Consumer Services","ville":"Tsengel","région":91,"date de l'emprunt":"05/06/2021","durée":8,"date de fin":"6/19/2022","taux de base":5.21,"discount":0.61,"taux bonifié":4.78,"condition (GWh/an)":3.817,"condition (tCO2/an)":101.37,"dernière date d'observation":"3/12/2022","réalisation (GWh)":198.29,"réalisation (tCO2)":173.25},
{"entreprise":"Wikivu","secteur d'activité":"Health Care","ville":"Doko","région":64,"date de l'emprunt":"20/12/2021","durée":12,"date de fin":"1/22/2023","taux de base":2.85,"discount":0.38,"taux bonifié":3.31,"condition (GWh/an)":4.502,"condition (tCO2/an)":101.29,"dernière date d'observation":"12/14/2022","réalisation (GWh)":14.74,"réalisation (tCO2)":70.64},
{"entreprise":"Babbleset","secteur d'activité":"Consumer Durables","ville":"Dul’durga","région":86,"date de l'emprunt":"12/05/2022","durée":3,"date de fin":"1/14/2023","taux de base":3.38,"discount":0.35,"taux bonifié":2.55,"condition (GWh/an)":3.705,"condition (tCO2/an)":168.93,"dernière date d'observation":"4/3/2022","réalisation (GWh)":176.8,"réalisation (tCO2)":39.4},
{"entreprise":"Dablist","secteur d'activité":"Capital Goods","ville":"Przybiernów","région":48,"date de l'emprunt":"14/11/2021","durée":2,"date de fin":"1/14/2023","taux de base":5.56,"discount":0.64,"taux bonifié":4.94,"condition (GWh/an)":5.655,"condition (tCO2/an)":130.34,"dernière date d'observation":"3/2/2022","réalisation (GWh)":179.71,"réalisation (tCO2)":67.69},
{"entreprise":"Rhyloo","secteur d'activité":"n/a","ville":"Sandviken","région":57,"date de l'emprunt":"21/11/2021","durée":14,"date de fin":"6/10/2022","taux de base":2.1,"discount":0.03,"taux bonifié":5.21,"condition (GWh/an)":5.677,"condition (tCO2/an)":156.69,"dernière date d'observation":"8/20/2022","réalisation (GWh)":158.53,"réalisation (tCO2)":14.36},
{"entreprise":"Feedmix","secteur d'activité":"Consumer Services","ville":"Huatanshan","région":80,"date de l'emprunt":"08/09/2021","durée":16,"date de fin":"6/23/2022","taux de base":3.59,"discount":0.8,"taux bonifié":3.8,"condition (GWh/an)":1.705,"condition (tCO2/an)":102.64,"dernière date d'observation":"4/18/2022","réalisation (GWh)":60.19,"réalisation (tCO2)":49.54},
{"entreprise":"Flashpoint","secteur d'activité":"Technology","ville":"Venezuela","région":28,"date de l'emprunt":"17/03/2022","durée":10,"date de fin":"5/6/2022","taux de base":4.96,"discount":0.76,"taux bonifié":4.66,"condition (GWh/an)":4.46,"condition (tCO2/an)":91.25,"dernière date d'observation":"2/23/2022","réalisation (GWh)":170.7,"réalisation (tCO2)":34.34},
{"entreprise":"Skyble","secteur d'activité":"Consumer Durables","ville":"Concord","région":74,"date de l'emprunt":"03/12/2022","durée":8,"date de fin":"12/29/2022","taux de base":3.21,"discount":0.08,"taux bonifié":4.99,"condition (GWh/an)":5.176,"condition (tCO2/an)":36.76,"dernière date d'observation":"9/14/2022","réalisation (GWh)":81.28,"réalisation (tCO2)":38.91},
{"entreprise":"Yoveo","secteur d'activité":"Capital Goods","ville":"Shuangta","région":23,"date de l'emprunt":"23/02/2021","durée":12,"date de fin":"12/12/2022","taux de base":5.38,"discount":0.52,"taux bonifié":5.5,"condition (GWh/an)":2.098,"condition (tCO2/an)":108.78,"dernière date d'observation":"9/12/2022","réalisation (GWh)":8.49,"réalisation (tCO2)":97.62},
{"entreprise":"Dablist","secteur d'activité":"Consumer Durables","ville":"Añelo","région":28,"date de l'emprunt":"21/09/2022","durée":16,"date de fin":"12/2/2022","taux de base":3.75,"discount":0.08,"taux bonifié":2.18,"condition (GWh/an)":3.053,"condition (tCO2/an)":46.22,"dernière date d'observation":"5/17/2022","réalisation (GWh)":172.88,"réalisation (tCO2)":58.85},
{"entreprise":"Centimia","secteur d'activité":"Finance","ville":"Sukaraharja","région":40,"date de l'emprunt":"27/01/2023","durée":7,"date de fin":"11/23/2022","taux de base":5.87,"discount":0.25,"taux bonifié":5.1,"condition (GWh/an)":4.389,"condition (tCO2/an)":49.53,"dernière date d'observation":"2/8/2023","réalisation (GWh)":10.28,"réalisation (tCO2)":115.56},
{"entreprise":"Leenti","secteur d'activité":"n/a","ville":"Lianran","région":2,"date de l'emprunt":"30/11/2022","durée":3,"date de fin":"2/12/2023","taux de base":2.37,"discount":0.66,"taux bonifié":3.36,"condition (GWh/an)":1.698,"condition (tCO2/an)":159.34,"dernière date d'observation":"12/18/2022","réalisation (GWh)":151.29,"réalisation (tCO2)":78.94},
{"entreprise":"Avaveo","secteur d'activité":"Energy","ville":"El Olivar","région":26,"date de l'emprunt":"20/08/2021","durée":17,"date de fin":"12/25/2022","taux de base":4.98,"discount":0.15,"taux bonifié":2.14,"condition (GWh/an)":1.079,"condition (tCO2/an)":9.85,"dernière date d'observation":"12/8/2022","réalisation (GWh)":128.45,"réalisation (tCO2)":82.29},
{"entreprise":"Flipstorm","secteur d'activité":"Technology","ville":"Frydek","région":78,"date de l'emprunt":"17/04/2021","durée":16,"date de fin":"11/9/2022","taux de base":2.13,"discount":0.42,"taux bonifié":4.65,"condition (GWh/an)":1.47,"condition (tCO2/an)":132.94,"dernière date d'observation":"3/6/2022","réalisation (GWh)":128.15,"réalisation (tCO2)":109.7},
{"entreprise":"Bluejam","secteur d'activité":"Consumer Non-Durables","ville":"Moulins","région":65,"date de l'emprunt":"30/05/2021","durée":18,"date de fin":"10/29/2022","taux de base":2.93,"discount":0.3,"taux bonifié":2.07,"condition (GWh/an)":2.045,"condition (tCO2/an)":147.85,"dernière date d'observation":"6/25/2022","réalisation (GWh)":152.11,"réalisation (tCO2)":187.75},
{"entreprise":"Riffwire","secteur d'activité":"Consumer Services","ville":"Baro Kunda","région":63,"date de l'emprunt":"18/04/2020","durée":2,"date de fin":"10/13/2022","taux de base":2.35,"discount":0.11,"taux bonifié":2.6,"condition (GWh/an)":5.016,"condition (tCO2/an)":75.11,"dernière date d'observation":"7/11/2022","réalisation (GWh)":192.2,"réalisation (tCO2)":51.3},
{"entreprise":"Jabbersphere","secteur d'activité":"Consumer Services","ville":"Chum Phae","région":50,"date de l'emprunt":"24/01/2022","durée":10,"date de fin":"8/7/2022","taux de base":2.18,"discount":0.13,"taux bonifié":3.69,"condition (GWh/an)":3.211,"condition (tCO2/an)":91.69,"dernière date d'observation":"1/8/2023","réalisation (GWh)":161.72,"réalisation (tCO2)":147.24},
{"entreprise":"Divavu","secteur d'activité":"Consumer Services","ville":"Hinvi","région":53,"date de l'emprunt":"13/11/2020","durée":10,"date de fin":"8/30/2022","taux de base":5.33,"discount":0.4,"taux bonifié":3.97,"condition (GWh/an)":3.931,"condition (tCO2/an)":16.6,"dernière date d'observation":"4/17/2022","réalisation (GWh)":121.79,"réalisation (tCO2)":108.52},
{"entreprise":"Realpoint","secteur d'activité":"n/a","ville":"Margacina","région":10,"date de l'emprunt":"30/06/2021","durée":13,"date de fin":"1/29/2023","taux de base":3.93,"discount":0.62,"taux bonifié":5.15,"condition (GWh/an)":1.839,"condition (tCO2/an)":85.02,"dernière date d'observation":"6/22/2022","réalisation (GWh)":41.47,"réalisation (tCO2)":197.62},
{"entreprise":"Plambee","secteur d'activité":"Health Care","ville":"Groningen","région":95,"date de l'emprunt":"15/09/2022","durée":18,"date de fin":"7/28/2022","taux de base":5.35,"discount":0.17,"taux bonifié":5.86,"condition (GWh/an)":5.817,"condition (tCO2/an)":199.82,"dernière date d'observation":"11/1/2022","réalisation (GWh)":39.92,"réalisation (tCO2)":189.62},
{"entreprise":"Dabjam","secteur d'activité":"Technology","ville":"Candating","région":25,"date de l'emprunt":"25/01/2022","durée":4,"date de fin":"5/15/2022","taux de base":2.95,"discount":0.79,"taux bonifié":2.41,"condition (GWh/an)":4.45,"condition (tCO2/an)":52.79,"dernière date d'observation":"9/4/2022","réalisation (GWh)":116.24,"réalisation (tCO2)":109.4},
{"entreprise":"Edgeclub","secteur d'activité":"Energy","ville":"Gombong","région":38,"date de l'emprunt":"29/10/2020","durée":18,"date de fin":"8/6/2022","taux de base":4.78,"discount":0.06,"taux bonifié":4.24,"condition (GWh/an)":3.674,"condition (tCO2/an)":102.34,"dernière date d'observation":"10/22/2022","réalisation (GWh)":184.01,"réalisation (tCO2)":127.68},
{"entreprise":"Mudo","secteur d'activité":"n/a","ville":"Upata","région":91,"date de l'emprunt":"16/03/2021","durée":3,"date de fin":"9/19/2022","taux de base":4.37,"discount":0.92,"taux bonifié":4.52,"condition (GWh/an)":1.77,"condition (tCO2/an)":76.59,"dernière date d'observation":"6/26/2022","réalisation (GWh)":8.39,"réalisation (tCO2)":171.59},
{"entreprise":"Pixoboo","secteur d'activité":"Health Care","ville":"Béthune","région":36,"date de l'emprunt":"07/09/2022","durée":5,"date de fin":"10/20/2022","taux de base":4.81,"discount":0.47,"taux bonifié":3.26,"condition (GWh/an)":0.934,"condition (tCO2/an)":166.25,"dernière date d'observation":"1/4/2023","réalisation (GWh)":99.92,"réalisation (tCO2)":176.88},
{"entreprise":"Jabbersphere","secteur d'activité":"Basic Industries","ville":"Kamenskiy","région":76,"date de l'emprunt":"21/06/2022","durée":11,"date de fin":"7/26/2022","taux de base":4.51,"discount":0.44,"taux bonifié":2.48,"condition (GWh/an)":4.404,"condition (tCO2/an)":157.26,"dernière date d'observation":"12/19/2022","réalisation (GWh)":41.44,"réalisation (tCO2)":160.84},
{"entreprise":"Miboo","secteur d'activité":"Capital Goods","ville":"Denver","région":44,"date de l'emprunt":"30/09/2020","durée":14,"date de fin":"2/13/2023","taux de base":2.22,"discount":0.22,"taux bonifié":3.3,"condition (GWh/an)":5.951,"condition (tCO2/an)":35.59,"dernière date d'observation":"12/17/2022","réalisation (GWh)":22.17,"réalisation (tCO2)":160.64},
{"entreprise":"Riffwire","secteur d'activité":"Consumer Services","ville":"Eyvān","région":42,"date de l'emprunt":"21/01/2023","durée":19,"date de fin":"4/5/2022","taux de base":5.58,"discount":0.33,"taux bonifié":5.21,"condition (GWh/an)":1.765,"condition (tCO2/an)":47.31,"dernière date d'observation":"4/17/2022","réalisation (GWh)":20.61,"réalisation (tCO2)":32.98},
{"entreprise":"Shuffletag","secteur d'activité":"Consumer Services","ville":"Xingzhen","région":87,"date de l'emprunt":"13/01/2023","durée":4,"date de fin":"4/10/2022","taux de base":5.09,"discount":0.86,"taux bonifié":4.7,"condition (GWh/an)":1.949,"condition (tCO2/an)":28.36,"dernière date d'observation":"8/14/2022","réalisation (GWh)":177.38,"réalisation (tCO2)":10.2},
{"entreprise":"Vinder","secteur d'activité":"Finance","ville":"Iktābah","région":34,"date de l'emprunt":"11/03/2021","durée":20,"date de fin":"7/23/2022","taux de base":2.1,"discount":0.75,"taux bonifié":3.83,"condition (GWh/an)":1.281,"condition (tCO2/an)":160.66,"dernière date d'observation":"6/24/2022","réalisation (GWh)":148.52,"réalisation (tCO2)":76.44},
{"entreprise":"Shufflebeat","secteur d'activité":"Health Care","ville":"Cheongsong gun","région":58,"date de l'emprunt":"09/08/2021","durée":7,"date de fin":"10/26/2022","taux de base":2.52,"discount":0.22,"taux bonifié":5.25,"condition (GWh/an)":1.391,"condition (tCO2/an)":81.74,"dernière date d'observation":"11/28/2022","réalisation (GWh)":167.01,"réalisation (tCO2)":30.78},
{"entreprise":"Devify","secteur d'activité":"n/a","ville":"Sukaharja","région":42,"date de l'emprunt":"14/07/2022","durée":11,"date de fin":"2/21/2022","taux de base":2.5,"discount":0.39,"taux bonifié":5.49,"condition (GWh/an)":2.015,"condition (tCO2/an)":191.55,"dernière date d'observation":"1/26/2023","réalisation (GWh)":87.66,"réalisation (tCO2)":129.08},
{"entreprise":"Jabberbean","secteur d'activité":"Consumer Non-Durables","ville":"Gudermes","région":5,"date de l'emprunt":"24/12/2022","durée":10,"date de fin":"11/11/2022","taux de base":4.22,"discount":0.57,"taux bonifié":2.2,"condition (GWh/an)":2.729,"condition (tCO2/an)":176.0,"dernière date d'observation":"7/20/2022","réalisation (GWh)":114.31,"réalisation (tCO2)":147.42},
{"entreprise":"Youtags","secteur d'activité":"Technology","ville":"San Lorenzo de Esmeraldas","région":52,"date de l'emprunt":"01/03/2022","durée":20,"date de fin":"7/25/2022","taux de base":2.94,"discount":0.97,"taux bonifié":3.95,"condition (GWh/an)":0.932,"condition (tCO2/an)":182.19,"dernière date d'observation":"5/6/2022","réalisation (GWh)":143.39,"réalisation (tCO2)":55.86},
{"entreprise":"Gabtune","secteur d'activité":"Consumer Services","ville":"Jiandou","région":71,"date de l'emprunt":"19/12/2022","durée":5,"date de fin":"11/26/2022","taux de base":3.08,"discount":0.62,"taux bonifié":2.34,"condition (GWh/an)":0.561,"condition (tCO2/an)":45.33,"dernière date d'observation":"1/20/2023","réalisation (GWh)":109.65,"réalisation (tCO2)":22.68},
{"entreprise":"Riffwire","secteur d'activité":"Consumer Non-Durables","ville":"São Bento do Sul","région":78,"date de l'emprunt":"14/08/2020","durée":15,"date de fin":"8/1/2022","taux de base":2.76,"discount":0.03,"taux bonifié":2.11,"condition (GWh/an)":2.597,"condition (tCO2/an)":173.98,"dernière date d'observation":"1/1/2023","réalisation (GWh)":2.53,"réalisation (tCO2)":79.36},
{"entreprise":"Quamba","secteur d'activité":"Capital Goods","ville":"Villa Nueva","région":65,"date de l'emprunt":"10/11/2021","durée":19,"date de fin":"5/31/2022","taux de base":3.35,"discount":0.14,"taux bonifié":4.22,"condition (GWh/an)":2.034,"condition (tCO2/an)":14.67,"dernière date d'observation":"5/30/2022","réalisation (GWh)":26.93,"réalisation (tCO2)":18.2},
{"entreprise":"Vidoo","secteur d'activité":"Miscellaneous","ville":"Besko","région":80,"date de l'emprunt":"19/07/2020","durée":10,"date de fin":"4/27/2022","taux de base":4.94,"discount":0.89,"taux bonifié":4.39,"condition (GWh/an)":0.98,"condition (tCO2/an)":184.95,"dernière date d'observation":"5/14/2022","réalisation (GWh)":112.1,"réalisation (tCO2)":161.64},
{"entreprise":"Gabvine","secteur d'activité":"Technology","ville":"Balayong","région":83,"date de l'emprunt":"01/08/2022","durée":13,"date de fin":"4/17/2022","taux de base":4.8,"discount":0.33,"taux bonifié":5.46,"condition (GWh/an)":1.064,"condition (tCO2/an)":32.2,"dernière date d'observation":"9/16/2022","réalisation (GWh)":152.25,"réalisation (tCO2)":110.56},
{"entreprise":"Leenti","secteur d'activité":"Transportation","ville":"Sindangpanji","région":40,"date de l'emprunt":"15/01/2023","durée":2,"date de fin":"2/18/2022","taux de base":3.32,"discount":0.41,"taux bonifié":5.92,"condition (GWh/an)":2.025,"condition (tCO2/an)":193.64,"dernière date d'observation":"6/15/2022","réalisation (GWh)":86.64,"réalisation (tCO2)":73.37},
{"entreprise":"Feedspan","secteur d'activité":"Energy","ville":"Tubigan","région":71,"date de l'emprunt":"29/06/2022","durée":17,"date de fin":"8/4/2022","taux de base":2.11,"discount":0.94,"taux bonifié":2.2,"condition (GWh/an)":0.783,"condition (tCO2/an)":70.25,"dernière date d'observation":"3/31/2022","réalisation (GWh)":176.56,"réalisation (tCO2)":175.03},
{"entreprise":"Wordtune","secteur d'activité":"Public Utilities","ville":"Buda-Kashalyova","région":59,"date de l'emprunt":"18/10/2021","durée":3,"date de fin":"7/5/2022","taux de base":3.29,"discount":0.15,"taux bonifié":3.34,"condition (GWh/an)":0.58,"condition (tCO2/an)":47.62,"dernière date d'observation":"10/22/2022","réalisation (GWh)":108.06,"réalisation (tCO2)":61.09},
{"entreprise":"Babbleset","secteur d'activité":"Finance","ville":"Rubizhne","région":2,"date de l'emprunt":"08/08/2021","durée":4,"date de fin":"12/31/2022","taux de base":4.78,"discount":0.86,"taux bonifié":2.87,"condition (GWh/an)":3.133,"condition (tCO2/an)":134.69,"dernière date d'observation":"5/18/2022","réalisation (GWh)":185.23,"réalisation (tCO2)":64.03},
{"entreprise":"Oloo","secteur d'activité":"Finance","ville":"Nongba","région":18,"date de l'emprunt":"24/03/2022","durée":18,"date de fin":"8/22/2022","taux de base":2.12,"discount":0.7,"taux bonifié":5.32,"condition (GWh/an)":4.255,"condition (tCO2/an)":52.26,"dernière date d'observation":"8/17/2022","réalisation (GWh)":26.32,"réalisation (tCO2)":108.41},
{"entreprise":"Yotz","secteur d'activité":"Basic Industries","ville":"Boca do Acre","région":28,"date de l'emprunt":"18/02/2020","durée":14,"date de fin":"10/4/2022","taux de base":2.44,"discount":0.8,"taux bonifié":5.4,"condition (GWh/an)":0.337,"condition (tCO2/an)":64.09,"dernière date d'observation":"11/17/2022","réalisation (GWh)":196.34,"réalisation (tCO2)":161.68},
{"entreprise":"Topiclounge","secteur d'activité":"Consumer Services","ville":"Midões","région":75,"date de l'emprunt":"23/03/2021","durée":15,"date de fin":"8/28/2022","taux de base":3.36,"discount":0.09,"taux bonifié":5.96,"condition (GWh/an)":0.3,"condition (tCO2/an)":24.9,"dernière date d'observation":"6/22/2022","réalisation (GWh)":190.36,"réalisation (tCO2)":171.66},
{"entreprise":"Tavu","secteur d'activité":"Finance","ville":"Kolor","région":92,"date de l'emprunt":"27/03/2020","durée":5,"date de fin":"3/30/2022","taux de base":4.22,"discount":0.82,"taux bonifié":4.79,"condition (GWh/an)":1.313,"condition (tCO2/an)":86.13,"dernière date d'observation":"11/20/2022","réalisation (GWh)":23.04,"réalisation (tCO2)":19.89},
{"entreprise":"Chatterpoint","secteur d'activité":"Consumer Services","ville":"Santa Bárbara","région":68,"date de l'emprunt":"21/09/2020","durée":10,"date de fin":"8/31/2022","taux de base":4.56,"discount":0.71,"taux bonifié":5.03,"condition (GWh/an)":5.638,"condition (tCO2/an)":73.55,"dernière date d'observation":"9/20/2022","réalisation (GWh)":87.62,"réalisation (tCO2)":143.69},
{"entreprise":"Voomm","secteur d'activité":"Technology","ville":"Orahovica","région":43,"date de l'emprunt":"10/09/2020","durée":12,"date de fin":"6/27/2022","taux de base":4.39,"discount":0.74,"taux bonifié":5.86,"condition (GWh/an)":5.205,"condition (tCO2/an)":54.08,"dernière date d'observation":"12/11/2022","réalisation (GWh)":101.82,"réalisation (tCO2)":149.35},
{"entreprise":"Meevee","secteur d'activité":"Health Care","ville":"Qulai","région":22,"date de l'emprunt":"23/06/2020","durée":4,"date de fin":"8/9/2022","taux de base":3.22,"discount":0.14,"taux bonifié":2.28,"condition (GWh/an)":0.135,"condition (tCO2/an)":33.7,"dernière date d'observation":"5/3/2022","réalisation (GWh)":136.66,"réalisation (tCO2)":187.87},
{"entreprise":"Youopia","secteur d'activité":"Consumer Services","ville":"Long Beach","région":34,"date de l'emprunt":"31/07/2022","durée":15,"date de fin":"3/17/2022","taux de base":2.73,"discount":0.68,"taux bonifié":2.19,"condition (GWh/an)":5.497,"condition (tCO2/an)":180.37,"dernière date d'observation":"11/12/2022","réalisation (GWh)":91.72,"réalisation (tCO2)":154.86}]